{
  "listen_addr": ":443",
  "domain": "zenpacs.com.tr",
  "tls": {
    "auto_cert": true,
    "acme_email": "admin@yourdomain.com"
  },
  "hospitals": [
    {
      "code": "ankara",
      "subdomain": "ankara.zenpacs.com.tr",
      "token": "CHANGE_ME_ANKARA"
    },
    {
      "code": "istanbul",
      "subdomain": "istanbul.zenpacs.com.tr",
      "token": "CHANGE_ME_ISTANBUL"
    },
    {
      "code": "samsun",
      "subdomain": "samsun.zenpacs.com.tr",
      "token": "CHANGE_ME_SAMSUN"
    }
  ],
  "idle_timeout": "30s",
  "max_concurrent_conn": 1000,
  "request_timeout": "30s",
  "metrics_addr": ":8080"
}